tracer/__init__.py
tracer/sdk.py
tracer_sdk-0.1.dist-info/METADATA
tracer_sdk-0.1.dist-info/WHEEL
tracer_sdk-0.1.dist-info/top_level.txt
tracer_sdk-0.1.dist-info/RECORD
